oauth_utils/__init__.py
oauth_utils/utils.py
bear_django_oauth_utils-0.1.0.dist-info/METADATA
bear_django_oauth_utils-0.1.0.dist-info/WHEEL
bear_django_oauth_utils-0.1.0.dist-info/top_level.txt
bear_django_oauth_utils-0.1.0.dist-info/RECORD
